tango_serial/__init__.py
tango_serial/core.py
tango_serial/tango/__init__.py
tango_serial/tango/server/__init__.py
tango_serial/tango/server/__main__.py
tango_serial/tango/server/serial_device.py
tango_serial-0.2.0.dist-info/LICENSE
tango_serial-0.2.0.dist-info/METADATA
tango_serial-0.2.0.dist-info/WHEEL
tango_serial-0.2.0.dist-info/entry_points.txt
tango_serial-0.2.0.dist-info/top_level.txt
tango_serial-0.2.0.dist-info/RECORD
