Metadata-Version: 2.1
Name: tango-serial
Version: 0.2.0
Summary: ALBA Python Serial with tango DeviceServer
Home-page: https://github.com/catunlock/tango_serial
Author: Alberto López Sánchez
Author-email: ctbeamlines@cells.es
License: GNU General Public License v3
Keywords: tango_serial
Platform: UNKNOWN
Classifier: Development Status :: 2 - Pre-Alpha
Classifier: Intended Audience :: Developers
Classifier: License :: OSI Approved :: GNU General Public License v3 (GPLv3)
Classifier: Natural Language :: English
Classifier: Programming Language :: Python :: 3
Classifier: Programming Language :: Python :: 3.5
Classifier: Programming Language :: Python :: 3.6
Classifier: Programming Language :: Python :: 3.7
Classifier: Programming Language :: Python :: 3.8
Classifier: Programming Language :: Python :: 3.9
Requires-Python: >=3.5
Requires-Dist: geventpyserialpytango
